mltb2/__init__.py
mltb2/arangodb.py
mltb2/bs.py
mltb2/data.py
mltb2/db.py
mltb2/fasttext.py
mltb2/files.py
mltb2/md.py
mltb2/openai.py
mltb2/optuna.py
mltb2/plot.py
mltb2/py.typed
mltb2/somajo.py
mltb2/somajo_transformers.py
mltb2/text.py
mltb2/transformers.py
mltb2-1.0.3.dist-info/LICENSE
mltb2-1.0.3.dist-info/METADATA
mltb2-1.0.3.dist-info/WHEEL
mltb2-1.0.3.dist-info/entry_points.txt
mltb2-1.0.3.dist-info/RECORD
