Metadata-Version: 2.3
Name: mltb2
Version: 1.0.3
Summary: Machine Learning Toolbox 2
Keywords: optuna,deep learning,ml,ai,machine learning,hyperparameter optimization,hyperparameter tuning,nlp,natural language processing,transformers,llm,large-language-models,openai,plot
Author: PhilipMay
Author-email: philip@may.la
Requires-Python: >=3.9,<4.0
Classifier: Development Status :: 3 - Alpha
Classifier: Intended Audience :: Developers
Classifier: Intended Audience :: Science/Research
Classifier: License :: OSI Approved :: MIT License
Classifier: Natural Language :: English
Classifier: Natural Language :: German
Classifier: Operating System :: OS Independent
Classifier: Programming Language :: Python :: 3
Classifier: Programming Language :: Python :: 3.9
Classifier: Programming Language :: Python :: 3.10
Classifier: Programming Language :: Python :: 3.11
Classifier: Programming Language :: Python :: 3.12
Classifier: Programming Language :: Python :: 3.13
Classifier: Programming Language :: Python :: 3 :: Only
Classifier: Topic :: Scientific/Engineering :: Artificial Intelligence
Classifier: Topic :: Scientific/Engineering :: Mathematics
Classifier: Topic :: Software Development :: Libraries :: Python Modules
Provides-Extra: arangodb
Provides-Extra: bs
Provides-Extra: data
Provides-Extra: fasttext
Provides-Extra: files
Provides-Extra: md
Provides-Extra: openai
Provides-Extra: optuna
Provides-Extra: plot
Provides-Extra: somajo
Provides-Extra: somajo-transformers
Provides-Extra: transformers
Requires-Dist: SoMaJo (>=2.4.1) ; extra == "somajo" or extra == "somajo-transformers"
Requires-Dist: azure-ai-ml ; extra == "openai"
Requires-Dist: azure-identity ; extra == "openai"
Requires-Dist: beautifulsoup4 (<4.13) ; extra == "data" or extra == "bs"
Requires-Dist: fasttext-wheel ; extra == "fasttext"
Requires-Dist: joblib ; extra == "files" or extra == "data"
Requires-Dist: jsonlines ; extra == "arangodb"
Requires-Dist: markdownify ; extra == "bs"
Requires-Dist: matplotlib ; extra == "plot"
Requires-Dist: mdformat ; extra == "bs"
Requires-Dist: numpy (>=1,<2)
Requires-Dist: openai (>=1,<2) ; extra == "openai"
Requires-Dist: optuna ; extra == "optuna"
Requires-Dist: pandas ; extra == "data"
Requires-Dist: platformdirs ; extra == "files" or extra == "fasttext" or extra == "data"
Requires-Dist: python-arango ; extra == "arangodb"
Requires-Dist: python-dotenv ; extra == "arangodb"
Requires-Dist: pyyaml ; extra == "openai"
Requires-Dist: safetensors (!=0.3.2) ; extra == "transformers" or extra == "md" or extra == "somajo-transformers"
Requires-Dist: scikit-learn ; extra == "files" or extra == "fasttext" or extra == "data" or extra == "transformers" or extra == "md" or extra == "somajo-transformers"
Requires-Dist: scipy
Requires-Dist: tiktoken ; extra == "openai"
Requires-Dist: torch (!=2.0.1,!=2.1.0,!=2.3.0) ; extra == "transformers" or extra == "md" or extra == "somajo-transformers"
Requires-Dist: tqdm
Requires-Dist: transformers ; extra == "transformers" or extra == "md" or extra == "somajo-transformers"
Project-URL: Bug Tracker, https://github.com/telekom/mltb2/issues
Project-URL: Documentation, https://telekom.github.io/mltb2/
Project-URL: Homepage, https://github.com/telekom/mltb2
